tabularmazemdp/__init__.py
tabularmazemdp/_version.py
tabularmazemdp/chrono.py
tabularmazemdp/maze.py
tabularmazemdp/maze_plotter.py
tabularmazemdp/mdp.py
tabularmazemdp/simple_action_space.py
tabularmazemdp/toolbox.py
tabularmazemdp-0.9.6.dist-info/LICENSE
tabularmazemdp-0.9.6.dist-info/METADATA
tabularmazemdp-0.9.6.dist-info/WHEEL
tabularmazemdp-0.9.6.dist-info/top_level.txt
tabularmazemdp-0.9.6.dist-info/RECORD
