Metadata-Version: 2.1
Name: tabularmazemdp
Version: 0.9.6
Summary: A simple maze to test dynamic programming and tabular reinforcement learning algorithms
Author-email: Olivier Sigaud <Olivier.Sigaud@isir.upmc.fr>, Mathis Koroglu <mathis.koroglu@isir.upmc.fr>
Project-URL: homepage, https://github.com/arlaz/TabularMazeMDP
License-File: LICENSE
Requires-Dist: numpy
Requires-Dist: matplotlib
